{"new":[{"id":"38BD2209-3095-4691-A214-96E94218DA3E","partition_index":0,"image_types":["cover","floating_action_button","background"],"primary_color":"#7ebee1","theme_name_en_us":"Pop Silhouette Dance","accent_color":"#f640c2","theme_description_ja_jp":"ポップシルエットダンス\nこの着せかえはncts.b0ba.teaさんからの「K-Pop」のリクエストで描きました。","version":"1.0","theme_name_ja_jp":"ポップシルエットダンス","theme_file_prefix":"gradient_silhouette_dance","artist_name_en_us":"Yoshihisa Masaki","theme_description_en_us":"Pop Silhouette Dance\nThis theme was drawn at the request of \"K-Pop\" from ncts.b0ba.tea.","artist_name_ja_jp":"正木祥悠"}],"delete":[],"update":[]}