{"new":[{"id":"A3406349-B116-484F-BAC7-07A39569AE66","partition_index":0,"image_types":["cover","floating_action_button","background"],"primary_color":"#fce5fd","theme_name_en_us":"Cherry (pink)","accent_color":"#fb95f7","theme_description_ja_jp":"さくらんぼ (ピンク)\nこの着せかえはelipさんからの「さくらんぼ、かわいい、ピンク」とHills Merinoさんからの「かわいいさくらんぼが着せかえ全体に広がったデザイン」のリクエストで描きました。","version":"1.0","theme_name_ja_jp":"さくらんぼ (ピンク)","theme_file_prefix":"cherry_pink","artist_name_en_us":"Yoshihisa Masaki","theme_description_en_us":"Cherry (pink)\nThis theme was drawn at the request of \"Cherry, cute, pink\" from elip and \"cute cherries all over the theme design\" from Hills Merino.","artist_name_ja_jp":"正木祥悠"},{"id":"D9BD7652-3B70-4A2C-B7ED-AD0A43192431","partition_index":0,"image_types":["cover","floating_action_button","background"],"primary_color":"#271a99","theme_name_en_us":"Cherry (navy)","accent_color":"#f5ecf5","theme_description_ja_jp":"さくらんぼ (紺色)\nこの着せかえはelipさんからの「さくらんぼ、かわいい、ピンク」とHills Merinoさんからの「かわいいさくらんぼが着せかえ全体に広がったデザイン」のリクエストで描きました。","version":"1.0","theme_name_ja_jp":"さくらんぼ (紺色)","theme_file_prefix":"cherry_navy","artist_name_en_us":"Yoshihisa Masaki","theme_description_en_us":"Cherry (navy)\nThis theme was drawn at the request of \"Cherry, cute, pink\" from elip and \"cute cherries all over the theme design\" from Hills Merino.","artist_name_ja_jp":"正木祥悠"},{"id":"AC74B230-2685-4DAF-AE4C-33998CEA228D","partition_index":0,"image_types":["cover","floating_action_button","background"],"primary_color":"#f0efe8","theme_name_en_us":"Cherry (ivory)","accent_color":"#eddf75","theme_description_ja_jp":"さくらんぼ (アイボリー)\nこの着せかえはelipさんからの「さくらんぼ、かわいい、ピンク」とHills Merinoさんからの「かわいいさくらんぼが着せかえ全体に広がったデザイン」のリクエストで描きました。","version":"1.0","theme_name_ja_jp":"さくらんぼ (アイボリー)","theme_file_prefix":"cherry_ivory","artist_name_en_us":"Yoshihisa Masaki","theme_description_en_us":"Cherry (ivory)\nThis theme was drawn at the request of \"Cherry, cute, pink\" from elip and \"cute cherries all over the theme design\" from Hills Merino.","artist_name_ja_jp":"正木祥悠"}],"delete":[],"update":[]}